[
  {
    "idProduct": 518,
    "idProductxPackingxBranchOffice": 1035,
    "barCode": "7591357020108",
    "referent": "518",
    "name": "AZUCAR MONTALBAN REFINADA DE PAPEL 1KG",
    "indPesado": false,
    "category": {
      "id": 779,
      "name": "VIVERES\u003E\u003EAZUCAR / ENDULZANTES\u003E\u003EAZUCAR BLANCA / REFINADA"
    },
    "status": {
      "id": 1,
      "name": "Activo"
    },
    "existence": 1,
    "productPacking": {
      "idProductBranchOfficePacking": 0,
      "idProduct": 0,
      "idPacking": 518,
      "idBranchOffice": 0,
      "idStatus": 0,
      "idSuplier": 0,
      "idReason": 0,
      "baseCost": 0,
      "conversionCost": 0,
      "baseNetCost": 40.8512,
      "conversionNetCost": 1.15,
      "netSellingCostBase": 40.8512,
      "netSellingCostConversion": 1.15,
      "basePVP": 53.24,
      "conversionPVP": 1.472,
      "indIva": true,
      "tax": 0,
      "pvpConversionTax": 1.472,
      "netFactor": 0,
      "netSalesFactor": 0,
      "sellingFactor": 1.28,
      "units": 1,
      "indActiveSale": false,
      "indActiveBuy": false,
      "indConsignment": false,
      "indOnline": false,
      "indShelf": false,
      "indTower": false,
      "createDate": "0001-01-01T00:00:00",
      "updateDate": "0001-01-01T00:00:00",
      "packingType": {
        "id": 2,
        "name": "Individual"
      },
      "packingPresentation": {
        "id": 1,
        "name": "UNIDAD"
      },
      "description": null,
      "product": null,
      "available": 0,
      "totalUnits": 0
    },
    "url": ""
  },
  {
    "idProduct": 1,
    "idProductxPackingxBranchOffice": 1001,
    "barCode": "1234567890123",
    "referent": "001",
    "name": "Leche Entera Lala 1L",
    "indPesado": false,
    "category": {
      "id": 100,
      "name": "Lácteos\u003E\u003ELeche"
    },
    "status": {
      "id": 1,
      "name": "Activo"
    },
    "existence": 100,
    "productPacking": {
      "idProductBranchOfficePacking": 0,
      "idProduct": 0,
      "idPacking": 100,
      "idBranchOffice": 0,
      "idStatus": 0,
      "idSuplier": 0,
      "idReason": 0,
      "baseCost": 0,
      "conversionCost": 0,
      "baseNetCost": 20.0,
      "conversionNetCost": 1.0,
      "netSellingCostBase": 22.0,
      "netSellingCostConversion": 1.0,
      "basePVP": 25.0,
      "conversionPVP": 1.0,
      "indIva": true,
      "tax": 0.0,
      "pvpConversionTax": 1.0,
      "netFactor": 0,
      "netSalesFactor": 0,
      "sellingFactor": 1.0,
      "units": 1.0,
      "indActiveSale": false,
      "indActiveBuy": false,
      "indConsignment": false,
      "indOnline": false,
      "indShelf": false,
      "indTower": false,
      "createDate": "0001-01-01T00:00:00",
      "updateDate": "0001-01-01T00:00:00",
      "packingType": {
        "id": 1,
        "name": "Botella"
      },
      "packingPresentation": {
        "id": 1,
        "name": "UNIDAD"
      },
      "description": null,
      "product": null,
      "available": 0,
      "totalUnits": 0
    },
    "url": ""
  },
  {
    "idProduct": 2,
    "idProductxPackingxBranchOffice": 1002,
    "barCode": "2345678901234",
    "referent": "002",
    "name": "Huevos Blancos San Juan 12 piezas",
    "indPesado": false,
    "category": {
      "id": 101,
      "name": "Lácteos\u003E\u003EHuevos"
    },
    "status": {
      "id": 1,
      "name": "Activo"
    },
    "existence": 50,
    "productPacking": {
      "idProductBranchOfficePacking": 0,
      "idProduct": 0,
      "idPacking": 101,
      "idBranchOffice": 0,
      "idStatus": 0,
      "idSuplier": 0,
      "idReason": 0,
      "baseCost": 0,
      "conversionCost": 0,
      "baseNetCost": 25.0,
      "conversionNetCost": 1.0,
      "netSellingCostBase": 27.0,
      "netSellingCostConversion": 1.0,
      "basePVP": 30.0,
      "conversionPVP": 1.0,
      "indIva": true,
      "tax": 0.0,
      "pvpConversionTax": 1.0,
      "netFactor": 0,
      "netSalesFactor": 0,
      "sellingFactor": 1.0,
      "units": 1.0,
      "indActiveSale": false,
      "indActiveBuy": false,
      "indConsignment": false,
      "indOnline": false,
      "indShelf": false,
      "indTower": false,
      "createDate": "0001-01-01T00:00:00",
      "updateDate": "0001-01-01T00:00:00",
      "packingType": {
        "id": 2,
        "name": "Caja"
      },
      "packingPresentation": {
        "id": 2,
        "name": "DOCENA"
      },
      "description": null,
      "product": null,
      "available": 0,
      "totalUnits": 0
    },
    "url": ""
  },
  {
    "idProduct": 3,
    "idProductxPackingxBranchOffice": 1003,
    "barCode": "3456789012345",
    "referent": "003",
    "name": "Arroz Blanco Luchetti 1kg",
    "indPesado": false,
    "category": {
      "id": 102,
      "name": "Granos\u003E\u003EArroz"
    },
    "status": {
      "id": 1,
      "name": "Activo"
    },
    "existence": 80,
    "productPacking": {
      "idProductBranchOfficePacking": 0,
      "idProduct": 0,
      "idPacking": 102,
      "idBranchOffice": 0,
      "idStatus": 0,
      "idSuplier": 0,
      "idReason": 0,
      "baseCost": 0,
      "conversionCost": 0,
      "baseNetCost": 15.0,
      "conversionNetCost": 1.0,
      "netSellingCostBase": 17.0,
      "netSellingCostConversion": 1.0,
      "basePVP": 20.0,
      "conversionPVP": 1.0,
      "indIva": true,
      "tax": 0.0,
      "pvpConversionTax": 1.0,
      "netFactor": 0,
      "netSalesFactor": 0,
      "sellingFactor": 1.0,
      "units": 1.0,
      "indActiveSale": false,
      "indActiveBuy": false,
      "indConsignment": false,
      "indOnline": false,
      "indShelf": false,
      "indTower": false,
      "createDate": "0001-01-01T00:00:00",
      "updateDate": "0001-01-01T00:00:00",
      "packingType": {
        "id": 3,
        "name": "Bolsa"
      },
      "packingPresentation": {
        "id": 3,
        "name": "1KG"
      },
      "description": null,
      "product": null,
      "available": 0,
      "totalUnits": 0
    },
    "url": ""
  },
  {
    "idProduct": 4,
    "idProductxPackingxBranchOffice": 1004,
    "barCode": "4567890123456",
    "referent": "004",
    "name": "Pan Integral Bimbo 600g",
    "indPesado": false,
    "category": {
      "id": 103,
      "name": "Panadería\u003E\u003EPan"
    },
    "status": {
      "id": 1,
      "name": "Activo"
    },
    "existence": 60,
    "productPacking": {
      "idProductBranchOfficePacking": 0,
      "idProduct": 0,
      "idPacking": 103,
      "idBranchOffice": 0,
      "idStatus": 0,
      "idSuplier": 0,
      "idReason": 0,
      "baseCost": 0,
      "conversionCost": 0,
      "baseNetCost": 12.0,
      "conversionNetCost": 1.0,
      "netSellingCostBase": 14.0,
      "netSellingCostConversion": 1.0,
      "basePVP": 16.0,
      "conversionPVP": 1.0,
      "indIva": true,
      "tax": 0.0,
      "pvpConversionTax": 1.0,
      "netFactor": 0,
      "netSalesFactor": 0,
      "sellingFactor": 1.0,
      "units": 1.0,
      "indActiveSale": false,
      "indActiveBuy": false,
      "indConsignment": false,
      "indOnline": false,
      "indShelf": false,
      "indTower": false,
      "createDate": "0001-01-01T00:00:00",
      "updateDate": "0001-01-01T00:00:00",
      "packingType": {
        "id": 4,
        "name": "Empaque"
      },
      "packingPresentation": {
        "id": 4,
        "name": "600g"
      },
      "description": null,
      "product": null,
      "available": 0,
      "totalUnits": 0
    },
    "url": ""
  },
  {
    "idProduct": 5,
    "idProductxPackingxBranchOffice": 1005,
    "barCode": "5678901234567",
    "referent": "005",
    "name": "Aceite de Oliva Extra Virgen Carbonell 1L",
    "indPesado": false,
    "category": {
      "id": 104,
      "name": "Aceites\u003E\u003EAceite de Oliva"
    },
    "status": {
      "id": 1,
      "name": "Activo"
    },
    "existence": 40,
    "productPacking": {
      "idProductBranchOfficePacking": 0,
      "idProduct": 0,
      "idPacking": 104,
      "idBranchOffice": 0,
      "idStatus": 0,
      "idSuplier": 0,
      "idReason": 0,
      "baseCost": 0,
      "conversionCost": 0,
      "baseNetCost": 30.0,
      "conversionNetCost": 1.0,
      "netSellingCostBase": 32.0,
      "netSellingCostConversion": 1.0,
      "basePVP": 35.0,
      "conversionPVP": 1.0,
      "indIva": true,
      "tax": 0.0,
      "pvpConversionTax": 1.0,
      "netFactor": 0,
      "netSalesFactor": 0,
      "sellingFactor": 1.0,
      "units": 1.0,
      "indActiveSale": false,
      "indActiveBuy": false,
      "indConsignment": false,
      "indOnline": false,
      "indShelf": false,
      "indTower": false,
      "createDate": "0001-01-01T00:00:00",
      "updateDate": "0001-01-01T00:00:00",
      "packingType": {
        "id": 5,
        "name": "Botella"
      },
      "packingPresentation": {
        "id": 5,
        "name": "1L"
      },
      "description": null,
      "product": null,
      "available": 0,
      "totalUnits": 0
    },
    "url": ""
  },
  {
    "idProduct": 6,
    "idProductxPackingxBranchOffice": 1006,
    "barCode": "6789012345678",
    "referent": "006",
    "name": "Yogur Natural Danone 1kg",
    "indPesado": false,
    "category": {
      "id": 105,
      "name": "Lácteos\u003E\u003EYogur"
    },
    "status": {
      "id": 1,
      "name": "Activo"
    },
    "existence": 70,
    "productPacking": {
      "idProductBranchOfficePacking": 0,
      "idProduct": 0,
      "idPacking": 105,
      "idBranchOffice": 0,
      "idStatus": 0,
      "idSuplier": 0,
      "idReason": 0,
      "baseCost": 0,
      "conversionCost": 0,
      "baseNetCost": 18.0,
      "conversionNetCost": 1.0,
      "netSellingCostBase": 20.0,
      "netSellingCostConversion": 1.0,
      "basePVP": 22.0,
      "conversionPVP": 1.0,
      "indIva": true,
      "tax": 0.0,
      "pvpConversionTax": 1.0,
      "netFactor": 0,
      "netSalesFactor": 0,
      "sellingFactor": 1.0,
      "units": 1.0,
      "indActiveSale": false,
      "indActiveBuy": false,
      "indConsignment": false,
      "indOnline": false,
      "indShelf": false,
      "indTower": false,
      "createDate": "0001-01-01T00:00:00",
      "updateDate": "0001-01-01T00:00:00",
      "packingType": {
        "id": 6,
        "name": "Envase"
      },
      "packingPresentation": {
        "id": 6,
        "name": "1KG"
      },
      "description": null,
      "product": null,
      "available": 0,
      "totalUnits": 0
    },
    "url": ""
  },
  {
    "idProduct": 7,
    "idProductxPackingxBranchOffice": 1007,
    "barCode": "7890123456789",
    "referent": "007",
    "name": "Pollo Entero Fresco 2kg",
    "indPesado": false,
    "category": {
      "id": 106,
      "name": "Carnes\u003E\u003EPollo"
    },
    "status": {
      "id": 1,
      "name": "Activo"
    },
    "existence": 30,
    "productPacking": {
      "idProductBranchOfficePacking": 0,
      "idProduct": 0,
      "idPacking": 106,
      "idBranchOffice": 0,
      "idStatus": 0,
      "idSuplier": 0,
      "idReason": 0,
      "baseCost": 0,
      "conversionCost": 0,
      "baseNetCost": 50.0,
      "conversionNetCost": 1.0,
      "netSellingCostBase": 55.0,
      "netSellingCostConversion": 1.0,
      "basePVP": 60.0,
      "conversionPVP": 1.0,
      "indIva": true,
      "tax": 0.0,
      "pvpConversionTax": 1.0,
      "netFactor": 0,
      "netSalesFactor": 0,
      "sellingFactor": 1.0,
      "units": 1.0,
      "indActiveSale": false,
      "indActiveBuy": false,
      "indConsignment": false,
      "indOnline": false,
      "indShelf": false,
      "indTower": false,
      "createDate": "0001-01-01T00:00:00",
      "updateDate": "0001-01-01T00:00:00",
      "packingType": {
        "id": 7,
        "name": "Empaque"
      },
      "packingPresentation": {
        "id": 7,
        "name": "2KG"
      },
      "description": null,
      "product": null,
      "available": 0,
      "totalUnits": 0
    },
    "url": ""
  },
  {
    "idProduct": 8,
    "idProductxPackingxBranchOffice": 1008,
    "barCode": "8901234567890",
    "referent": "008",
    "name": "Cereal Corn Flakes Kellogg's 500g",
    "indPesado": false,
    "category": {
      "id": 107,
      "name": "Cereales\u003E\u003ECereal de Maíz"
    },
    "status": {
      "id": 1,
      "name": "Activo"
    },
    "existence": 90,
    "productPacking": {
      "idProductBranchOfficePacking": 0,
      "idProduct": 0,
      "idPacking": 107,
      "idBranchOffice": 0,
      "idStatus": 0,
      "idSuplier": 0,
      "idReason": 0,
      "baseCost": 0,
      "conversionCost": 0,
      "baseNetCost": 10.0,
      "conversionNetCost": 1.0,
      "netSellingCostBase": 12.0,
      "netSellingCostConversion": 1.0,
      "basePVP": 15.0,
      "conversionPVP": 1.0,
      "indIva": true,
      "tax": 0.0,
      "pvpConversionTax": 1.0,
      "netFactor": 0,
      "netSalesFactor": 0,
      "sellingFactor": 1.0,
      "units": 1.0,
      "indActiveSale": false,
      "indActiveBuy": false,
      "indConsignment": false,
      "indOnline": false,
      "indShelf": false,
      "indTower": false,
      "createDate": "0001-01-01T00:00:00",
      "updateDate": "0001-01-01T00:00:00",
      "packingType": {
        "id": 8,
        "name": "Caja"
      },
      "packingPresentation": {
        "id": 8,
        "name": "500g"
      },
      "description": null,
      "product": null,
      "available": 0,
      "totalUnits": 0
    },
    "url": ""
  },
  {
    "idProduct": 9,
    "idProductxPackingxBranchOffice": 1009,
    "barCode": "9012345678901",
    "referent": "009",
    "name": "Manzanas Gala (1kg)",
    "indPesado": true,
    "category": {
      "id": 108,
      "name": "Frutas\u003E\u003EManzanas"
    },
    "status": {
      "id": 1,
      "name": "Activo"
    },
    "existence": 120,
    "productPacking": {
      "idProductBranchOfficePacking": 0,
      "idProduct": 0,
      "idPacking": 108,
      "idBranchOffice": 0,
      "idStatus": 0,
      "idSuplier": 0,
      "idReason": 0,
      "baseCost": 0,
      "conversionCost": 0,
      "baseNetCost": 10.0,
      "conversionNetCost": 1.0,
      "netSellingCostBase": 12.0,
      "netSellingCostConversion": 1.0,
      "basePVP": 15.0,
      "conversionPVP": 1.0,
      "indIva": true,
      "tax": 0.0,
      "pvpConversionTax": 1.0,
      "netFactor": 0,
      "netSalesFactor": 0,
      "sellingFactor": 1.0,
      "units": 1.0,
      "indActiveSale": false,
      "indActiveBuy": false,
      "indConsignment": false,
      "indOnline": false,
      "indShelf": false,
      "indTower": false,
      "createDate": "0001-01-01T00:00:00",
      "updateDate": "0001-01-01T00:00:00",
      "packingType": {
        "id": 9,
        "name": "Bolsa"
      },
      "packingPresentation": {
        "id": 9,
        "name": "1KG"
      },
      "description": null,
      "product": null,
      "available": 0,
      "totalUnits": 0
    },
    "url": ""
  },
  {
    "idProduct": 10,
    "idProductxPackingxBranchOffice": 1010,
    "barCode": "0123456789012",
    "referent": "010",
    "name": "Pasta Spaghetti Barilla 500g",
    "indPesado": false,
    "category": {
      "id": 109,
      "name": "Pastas\u003E\u003ESpaghetti"
    },
    "status": {
      "id": 1,
      "name": "Activo"
    },
    "existence": 70,
    "productPacking": {
      "idProductBranchOfficePacking": 0,
      "idProduct": 0,
      "idPacking": 109,
      "idBranchOffice": 0,
      "idStatus": 0,
      "idSuplier": 0,
      "idReason": 0,
      "baseCost": 0,
      "conversionCost": 0,
      "baseNetCost": 8.0,
      "conversionNetCost": 1.0,
      "netSellingCostBase": 10.0,
      "netSellingCostConversion": 1.0,
      "basePVP": 12.0,
      "conversionPVP": 1.0,
      "indIva": true,
      "tax": 0.0,
      "pvpConversionTax": 1.0,
      "netFactor": 0,
      "netSalesFactor": 0,
      "sellingFactor": 1.0,
      "units": 1.0,
      "indActiveSale": false,
      "indActiveBuy": false,
      "indConsignment": false,
      "indOnline": false,
      "indShelf": false,
      "indTower": false,
      "createDate": "0001-01-01T00:00:00",
      "updateDate": "0001-01-01T00:00:00",
      "packingType": {
        "id": 10,
        "name": "Paquete"
      },
      "packingPresentation": {
        "id": 10,
        "name": "500g"
      },
      "description": null,
      "product": null,
      "available": 0,
      "totalUnits": 0
    },
    "url": ""
  }
]